funniest/__init__.py
funniestyyy-3.0.0.dist-info/METADATA
funniestyyy-3.0.0.dist-info/WHEEL
funniestyyy-3.0.0.dist-info/top_level.txt
funniestyyy-3.0.0.dist-info/RECORD
