Metadata-Version: 2.1
Name: funniestyyy
Version: 3.0.0
Summary: The funniest joke in the world
Home-page: http://github.com/storborg/funniest
Author: Flying Circus
Author-email: flyingcircus@example.com
License: MIT
Platform: UNKNOWN
